{
  "applications": "*",
  "changelogDate": "20231001020412",
  "databaseType": "sql",
  "dto": "mapstruct",
  "embedded": false,
  "entityTableName": "wkf_user_backup",
  "fields": [
    {
      "fieldName": "wkfUserBackupId",
      "fieldType": "Long",
      "fieldValidateRules": ["required"]
    },
    {
      "fieldName": "wkfBeginDate",
      "fieldType": "LocalDate",
      "fieldValidateRules": ["required"]
    },
    {
      "fieldName": "wkfEndDate",
      "fieldType": "LocalDate"
    },
    {
      "fieldName": "wkfUserIdBackup",
      "fieldType": "String",
      "fieldValidateRules": ["required", "maxlength"],
      "fieldValidateRulesMaxlength": "255"
    },
    {
      "fieldName": "wkfUserIdOff",
      "fieldType": "String",
      "fieldValidateRules": ["required", "maxlength"],
      "fieldValidateRulesMaxlength": "255"
    }
  ],
  "fluentMethods": true,
  "jpaMetamodelFiltering": false,
  "name": "WkfUserBackup",
  "pagination": "pagination",
  "readOnly": false,
  "relationships": [],
  "service": "serviceClass"
}
